migrations/README
migrations/__init__.py
migrations/alembic.ini
migrations/apply.py
migrations/env.py
migrations/script.py.mako
migrations/__pycache__/env.cpython-39.pyc
migrations/versions/5ab22b567bb4_.py
migrations/versions/9ced6e9ebd70_.py
migrations/versions/__init__.py
migrations/versions/ec190bd5da74_.py
migrations/versions/__pycache__/5ab22b567bb4_.cpython-39.pyc
migrations/versions/__pycache__/9ced6e9ebd70_.cpython-39.pyc
migrations/versions/__pycache__/ec190bd5da74_.cpython-39.pyc
vm_booking_api/__init__.py
vm_booking_api/app.py
vm_booking_api/config.py
vm_booking_api/constants.py
vm_booking_api/manage.py
vm_booking_api/models.py
vm_booking_api/migrations/README
vm_booking_api/migrations/__init__.py
vm_booking_api/migrations/alembic.ini
vm_booking_api/migrations/apply.py
vm_booking_api/migrations/env.py
vm_booking_api/migrations/script.py.mako
vm_booking_api/migrations/__pycache__/env.cpython-39.pyc
vm_booking_api/migrations/versions/5ab22b567bb4_.py
vm_booking_api/migrations/versions/9ced6e9ebd70_.py
vm_booking_api/migrations/versions/__init__.py
vm_booking_api/migrations/versions/ec190bd5da74_.py
vm_booking_api/migrations/versions/__pycache__/5ab22b567bb4_.cpython-39.pyc
vm_booking_api/migrations/versions/__pycache__/9ced6e9ebd70_.cpython-39.pyc
vm_booking_api/migrations/versions/__pycache__/ec190bd5da74_.cpython-39.pyc
vm_booking_app-0.1.69.dist-info/METADATA
vm_booking_app-0.1.69.dist-info/WHEEL
vm_booking_app-0.1.69.dist-info/entry_points.txt
vm_booking_app-0.1.69.dist-info/top_level.txt
vm_booking_app-0.1.69.dist-info/RECORD
