Metadata-Version: 2.1
Name: vm-booking-app
Version: 0.1.69
Summary: A flask based vm booking app.
Home-page: https://gitlab.jdobc.link/oonyshchenko/vm-booking-app
Author: Oleksandr Onyshchenko
Author-email: alex.dev936@gmail.com
License: MIT
Platform: UNKNOWN
Classifier: License :: OSI Approved :: MIT License
Classifier: Programming Language :: Python
Classifier: Programming Language :: Python :: 3
Classifier: Programming Language :: Python :: 3.7
Classifier: Programming Language :: Python :: Implementation :: CPython
Classifier: Programming Language :: Python :: Implementation :: PyPy
Requires-Python: >=3.7.0
Requires-Dist: flask
Requires-Dist: psycopg2-binary
Requires-Dist: flask-sqlalchemy
Requires-Dist: flask-migrate
Requires-Dist: sqlalchemy-serializer
Requires-Dist: flask-script
